odoo/addons/sale_blanket_order_crm_tags/LICENSE
odoo/addons/sale_blanket_order_crm_tags/README.rst
odoo/addons/sale_blanket_order_crm_tags/__init__.py
odoo/addons/sale_blanket_order_crm_tags/__manifest__.py
odoo/addons/sale_blanket_order_crm_tags/images/screen.png
odoo/addons/sale_blanket_order_crm_tags/models/__init__.py
odoo/addons/sale_blanket_order_crm_tags/models/blanket_order.py
odoo/addons/sale_blanket_order_crm_tags/static/description/icon.png
odoo/addons/sale_blanket_order_crm_tags/static/description/index.html
odoo/addons/sale_blanket_order_crm_tags/tests/TEST_INSTRUCTIONS.rst
odoo/addons/sale_blanket_order_crm_tags/views/view_blanket_order_form.xml
odoo/addons/sale_blanket_order_crm_tags/wizard/__init__.py
odoo/addons/sale_blanket_order_crm_tags/wizard/create_sale_orders.py
odoo_addon_sale_blanket_order_crm_tags-16.0.1.0.0.dist-info/METADATA
odoo_addon_sale_blanket_order_crm_tags-16.0.1.0.0.dist-info/WHEEL
odoo_addon_sale_blanket_order_crm_tags-16.0.1.0.0.dist-info/top_level.txt
odoo_addon_sale_blanket_order_crm_tags-16.0.1.0.0.dist-info/RECORD
